cvmd/__init__.py
cvmd/__init__.pyi
cvmd/registry.py
cvmd/detr/__init__.py
cvmd/detr/deformable_detr.py
cvmd/detr/detr.py
cvmd/utils/imageutils.py
cvmd/utils/ray_infer.py
cvmd/utils/torchutils.py
cvmd/utils/windows.py
cvmd/yolo/__init__.py
cvmd/yolo/metrics.py
cvmd/yolo/ops.py
cvmd/yolo/v5ops.py
cvmd/yolo/yolov11.py
cvmd/yolo/yolov12.py
cvmd/yolo/yolov5.py
cvmd/yolo/yolov8.py
cvmd-0.1.0.post202601042351.dist-info/METADATA
cvmd-0.1.0.post202601042351.dist-info/WHEEL
cvmd-0.1.0.post202601042351.dist-info/top_level.txt
cvmd-0.1.0.post202601042351.dist-info/RECORD
