Metadata-Version: 2.4
Name: cvmd
Version: 0.1.0.post202601042351
Summary: Computer Vision Models Deployment
Requires-Python: >=3.10
